<?xml version="1.0" ?>
<State openmmVersion="7.5.1" time="2199.9999999618008" type="State" version="1">
	<PeriodicBoxVectors>
		<A x="3.4000000000000004" y="0" z="0"/>
		<B x="0" y="3.4000000000000004" z="0"/>
		<C x="0" y="0" z="3.4000000000000004"/>
	</PeriodicBoxVectors>
	<Parameters lambda_electrostatics="0" lambda_sterics=".7"/>
	<Positions>
		<Position x=".30096305133577733" y=".5804352135320079" z="-.18648677776550554"/>
		<Position x=".3404071564242846" y=".5046316162759722" z="-.11946486179468044"/>
		<Position x=".3860095922389808" y=".37883882053669066" z="-.15631235329501983"/>
		<Position x=".4296118440218626" y=".29022263874097454" z="-.057770721440616485"/>
		<Position x=".4143309066889441" y=".32114561851720236" z=".08226131984738931"/>
		<Position x=".3665546409925921" y=".4452129773069948" z=".11536351929946813"/>
		<Position x=".32466737050166805" y=".5393088635677541" z=".018947306525374647"/>
		<Position x=".2737401824257997" y=".6310859193255577" z=".04682836737827366"/>
		<Position x=".3491700014066494" y=".44874649265747546" z=".2627328618229787"/>
		<Position x=".3939861298196369" y=".32641421848050917" z=".30861440146183744"/>
		<Position x=".43802316402292274" y=".2505081596096211" z=".19752835961976728"/>
		<Position x=".47780424541229954" y=".1578355120233275" z=".20302799168369706"/>
		<Position x=".42663636400552607" y=".30220170628754145" z=".45794167321886925"/>
		<Position x=".4020827276145435" y=".1582998945936375" z=".5137185926484463"/>
		<Position x=".41907506061710176" y=".16282105585985987" z=".6641246259517283"/>
		<Position x=".35641251083883" y=".304809837806915" z=".7016361975983597"/>
		<Position x=".3435028779533193" y=".3772990712270642" z=".5669273451253338"/>
		<Position x=".3691836639796431" y=".48390775023965643" z=".5699560811436014"/>
		<Position x=".23674475532403774" y=".37697599462082737" z=".5416946590333709"/>
		<Position x=".4057523873490047" y=".36313397502965883" z=".7803633192751063"/>
		<Position x=".2543578442418172" y=".2817419474936146" z=".7346029480568168"/>
		<Position x=".5233666334186696" y=".16000891115097293" z=".6980281621407459"/>
		<Position x=".36607579527844797" y=".07715631515314866" z=".7075610186057697"/>
		<Position x=".30290142445281265" y=".12532374966287357" z=".48040593389887043"/>
		<Position x=".4726647261972667" y=".08687191745064143" z=".46955621690645094"/>
		<Position x=".5320082423214977" y=".3289502880011114" z=".4726171846789281"/>
		<Position x=".32583785824965944" y=".5332693755924599" z=".32646710188869404"/>
		<Position x=".45804630643343314" y=".18721736817184012" z="-.07714481721279402"/>
		<Position x=".4033047914091368" y=".35687929085716624" z="-.26125336120860915"/>
	</Positions>
	<Velocities>
		<Velocity x="-2.9701633147563022" y="2.1896227376707045" z="2.8257715230107507"/>
		<Velocity x=".4805252686121697" y=".5645232752685136" z="-.646155908979422"/>
		<Velocity x="-.2794940917083266" y="-.5960361973924577" z=".5931839941270278"/>
		<Velocity x=".40103353744319614" y=".37464912514287296" z=".10345922237218336"/>
		<Velocity x=".0685948702943695" y="-.4882169231968103" z=".10957467996967896"/>
		<Velocity x=".37692665918120927" y="-.7439329008069595" z=".07366270500478583"/>
		<Velocity x=".06647496939865549" y=".4521587474351496" z=".18791562819170382"/>
		<Velocity x="-1.3534624650161087" y=".703355237971548" z="-2.8311105694582284"/>
		<Velocity x="-.6318442590300122" y="-.8533895616234244" z=".6384440637057232"/>
		<Velocity x="-.26026393138403603" y=".9706912607061746" z="-.130679896041902"/>
		<Velocity x="-.5743423747850696" y="-.10192366904948624" z="-.5888777964391106"/>
		<Velocity x="1.3350085603239525" y=".49409115524114144" z="-2.7667799715343637"/>
		<Velocity x=".48647884587563195" y=".8373729640989702" z="-.004971590996549757"/>
		<Velocity x="-.06714654922532204" y=".4277838180511695" z=".27279647625738646"/>
		<Velocity x=".5509769908579043" y="-.38206675304008897" z="-.19003204475687152"/>
		<Velocity x="-.20761123410703575" y="-.23137624474803276" z=".2661224779173521"/>
		<Velocity x=".010893332628658658" y="-.0705712864133845" z="-.4450573751132447"/>
		<Velocity x=".38763998755714235" y="-.17455256831025445" z="1.924258475367091"/>
		<Velocity x="-.11314325185321494" y="-1.888749406445206" z="-.035290757479489177"/>
		<Velocity x="-2.127420577449801" y="1.743940265552496" z=".10263095089030339"/>
		<Velocity x="-.7156694160723176" y="-2.7907242597783046" z="-2.6355957295252086"/>
		<Velocity x="1.0071645939007667" y="-1.4307679821903008" z="-1.584385189581483"/>
		<Velocity x=".5231631498163747" y="-.791798565952885" z="-1.0125789503950267"/>
		<Velocity x="-.11092732805384475" y=".12265651380208298" z=".6969360974606043"/>
		<Velocity x="-.5566601416787664" y="-.3599857190441508" z=".740144910426066"/>
		<Velocity x=".7379848873487749" y=".2853808532256863" z="-.7425713653296806"/>
		<Velocity x=".5874628233079882" y="-.5679865447148491" z=".731058391184175"/>
		<Velocity x=".815710194749103" y=".5976815860415652" z="-.5042283183631022"/>
		<Velocity x="-1.5826584855918313" y=".0348839089041042" z=".2251203975108529"/>
	</Velocities>
	<Forces>
		<Force x="372.6626120885328" y="-423.4719465968272" z="-705.1794676960502"/>
		<Force x="-1268.2699069589025" y="1602.7638149074512" z="2113.600771702832"/>
		<Force x="1130.1185330862122" y="149.87215063934514" z="-709.0026471534413"/>
		<Force x="-362.39881466391137" y="-1740.32195718347" z="2773.4278433881946"/>
		<Force x="-102.97453217132367" y="1600.1890589573652" z="-2199.8744701854876"/>
		<Force x="-1009.7940632526133" y="347.4422302168773" z="1593.937999057605"/>
		<Force x="349.19013537946546" y="-928.5083279205646" z="-876.9280758727086"/>
		<Force x="218.5853848801714" y="95.76485075515133" z="109.6502584421631"/>
		<Force x="490.5468711803339" y="139.7275373447299" z="-1360.9252853781115"/>
		<Force x="338.89297505345877" y="-118.60095217693714" z="808.2769238614696"/>
		<Force x="-101.47886363048227" y="-774.0488894969822" z="546.4580528982365"/>
		<Force x="81.30207073969169" y="33.99059932041466" z="-55.10417103588718"/>
		<Force x="-579.6768428354242" y="-623.8088970646919" z="603.3045230700617"/>
		<Force x="1079.1034646899689" y="-91.43322862221548" z="-2097.7218051657483"/>
		<Force x="-760.5940481785417" y="1584.5082009661385" z="1061.827699682984"/>
		<Force x="-153.51102517436462" y="-1929.0580559597288" z="-530.9919593203832"/>
		<Force x="-121.9543202031665" y="1081.812095834985" z="-939.2044790865781"/>
		<Force x="239.58247043529212" y="-53.46427809373999" z="266.4372092174669"/>
		<Force x="9.952833486812716" y="-123.94514553675896" z="-255.64404011494253"/>
		<Force x="315.14124071933054" y="-156.1617857902648" z="-70.44395663240353"/>
		<Force x="-2.610098765505428" y="268.3322039803402" z="294.6333085574925"/>
		<Force x="109.2851343820751" y="-51.35672955931138" z="-287.3085330420927"/>
		<Force x="-38.44978924522991" y="138.1636375959533" z="266.0221677832303"/>
		<Force x="-167.8477183038653" y="-32.68809907359918" z="380.1959817280831"/>
		<Force x="75.31728602378969" y="38.938244510980226" z="22.222731845969673"/>
		<Force x="46.506582230930974" y="-97.25355698251619" z="93.90850344775247"/>
		<Force x="-157.82088346495297" y="66.33204389704369" z="-143.37937768193638"/>
		<Force x="342.676894681671" y="217.21239673917205" z="-685.9918338038656"/>
		<Force x="-371.4835822094528" y="-220.9272156083397" z="-16.203872513907317"/>
	</Forces>
	<IntegratorParameters/>
</State>
