<?xml version="1.0" ?>
<State openmmVersion="7.5.1" time="2199.9999999618008" type="State" version="1">
	<PeriodicBoxVectors>
		<A x="3.4000000000000004" y="0" z="0"/>
		<B x="0" y="3.4000000000000004" z="0"/>
		<C x="0" y="0" z="3.4000000000000004"/>
	</PeriodicBoxVectors>
	<Parameters lambda_electrostatics="0" lambda_sterics=".35"/>
	<Positions>
		<Position x=".6317667170574959" y="-.03758318135759464" z=".48184793267089465"/>
		<Position x=".5723913216231806" y=".05243401879981665" z=".46898612504578985"/>
		<Position x=".5123488646475741" y=".12010232210147849" z=".5751820472107657"/>
		<Position x=".43259635444697864" y=".23181952977786657" z=".5496830685380345"/>
		<Position x=".4186432127356761" y=".27767511721442917" z=".4170426260295536"/>
		<Position x=".47799095678349973" y=".21035922965300624" z=".3131672579904432"/>
		<Position x=".5484728408649687" y=".09326262811202451" z=".3345717096211332"/>
		<Position x=".5792804246013074" y=".03245025852404809" z=".2500335023432765"/>
		<Position x=".4358678552513549" y=".27586633529034915" z=".19321061988697705"/>
		<Position x=".37099037262470536" y=".39040199526209746" z=".2309736204738434"/>
		<Position x=".3700474089615587" y=".39488566828048144" z=".36978600929306316"/>
		<Position x=".34991888246351843" y=".4740931016840755" z=".4291326597010644"/>
		<Position x=".32865876347040063" y=".4975904523122126" z=".1276773557368459"/>
		<Position x=".2643843544011659" y=".6168954467544198" z=".194333864192369"/>
		<Position x=".16945638113270015" y=".6747157653852506" z=".09013188092322605"/>
		<Position x=".11606624650150019" y=".5403279932224793" z=".023338888539468597"/>
		<Position x=".2300744555368797" y=".4389693344446693" z=".021027001145797752"/>
		<Position x=".2687699129553069" y=".43923795280288697" z="-.08162132977775693"/>
		<Position x=".19823383070211448" y=".3360579591421791" z=".04175171463584082"/>
		<Position x=".08792950343494632" y=".5607364361245869" z="-.080708742614727"/>
		<Position x=".034070528354688996" y=".5074486119459521" z=".08837540309949087"/>
		<Position x=".22803097826924887" y=".7415665147426755" z=".025835052802652903"/>
		<Position x=".08692840335742001" y=".7329277664650699" z=".13296394874056797"/>
		<Position x=".20501313616220793" y=".5826195210448585" z=".2799744417537933"/>
		<Position x=".33897610701927416" y=".6917863737669011" z=".22368533861174802"/>
		<Position x=".4189582347292204" y=".5409955831778626" z=".08299973144436341"/>
		<Position x=".4593100782678091" y=".25043954278881086" z=".0904755216814918"/>
		<Position x=".3985346217921124" y=".285242089404196" z=".6378861778458096"/>
		<Position x=".5271329160751448" y=".0842373403465604" z=".6766172231208529"/>
	</Positions>
	<Velocities>
		<Velocity x="-1.7277692359429775" y="-.8794996660120603" z=".284716145288022"/>
		<Velocity x="-.0443251804614353" y=".3793062482157286" z=".9458483343778301"/>
		<Velocity x="-.4754220060416148" y=".5995752678322961" z=".5709488029179699"/>
		<Velocity x="-.05770693734197252" y="-.7702806638731075" z=".5079043568660402"/>
		<Velocity x=".1678270198281484" y="-.36595316331602956" z="-.6575456920221712"/>
		<Velocity x="-.6521648438258532" y="-.5234114219047348" z="-.1093166827005887"/>
		<Velocity x="-.10337283127137553" y="-.24179198844429678" z="-.10915381312176509"/>
		<Velocity x="-2.052344771908854" y="-.16315354104008348" z="-.9289252482984622"/>
		<Velocity x=".3289656874723157" y=".9133723903846647" z="-.04844896047064007"/>
		<Velocity x="-.1065464511547376" y=".07100237683760335" z="-.25017211325899236"/>
		<Velocity x="-.41303261772396294" y="-.42316972026124056" z="-.2640912896961778"/>
		<Velocity x=".8188474063027529" y="1.4522009612712439" z="-2.2011924309902065"/>
		<Velocity x=".10759466497686776" y=".09715615103347841" z="-.4773736405900564"/>
		<Velocity x=".3418146605349559" y="-.024884413732051414" z=".8928577187763964"/>
		<Velocity x=".5173932884178362" y=".23678716135766553" z=".3335446739082745"/>
		<Velocity x=".14752345476649192" y=".4600997573055432" z="-.5290639317489364"/>
		<Velocity x=".28336926050340216" y="-.03718571881031196" z="-.14893092563883492"/>
		<Velocity x="1.7453939879947533" y=".33341697715480456" z=".3783087673186192"/>
		<Velocity x=".7887358507723402" y=".1346941766711407" z="1.6510818039252653"/>
		<Velocity x=".44030603267481566" y="-1.1235641056529522" z="-.9454731139865378"/>
		<Velocity x="-.3927952448836841" y=".6504196748735591" z="-1.103923685335524"/>
		<Velocity x=".9410175991418634" y="-.2899216183310793" z=".16429032281382006"/>
		<Velocity x="-1.881627106909388" y="-2.2590121142179176" z="-.5968643373219368"/>
		<Velocity x="-.40604268792814036" y=".15800810750243865" z=".45674800920533776"/>
		<Velocity x=".7262100807433058" y="1.6846661068177227" z="-3.6410329215357944"/>
		<Velocity x="1.7780227478427224" y="-1.2104852882551254" z="1.4449497261004725"/>
		<Velocity x="-1.6208877165247715" y="-.3546409543298823" z="-.2325248662666396"/>
		<Velocity x="-.43169814967344844" y="2.354620774573768" z="-1.3766396132186554"/>
		<Velocity x=".7212879115515713" y="-2.101124446044121" z="-.461831357971787"/>
	</Velocities>
	<Forces>
		<Force x="-67.47135826158055" y="16.82489550755519" z="457.19000931108934"/>
		<Force x="-14.82837673179167" y="-491.8100281960618" z="-1718.0223325434354"/>
		<Force x="75.72922375437044" y="-330.9685810746963" z="143.1965479530955"/>
		<Force x="265.22247553405873" y="675.8236414475598" z="558.1581321681044"/>
		<Force x="1249.048637657878" y="-954.2293657364262" z="326.1409322641415"/>
		<Force x="-1134.4185358473228" y="156.55276781625426" z="425.11452773083715"/>
		<Force x="241.78230011781056" y="-590.892262317982" z="422.1367311645937"/>
		<Force x="347.5113906043932" y="77.38953161750557" z="63.1872593510651"/>
		<Force x="648.2585966754654" y="-302.77697559349934" z="-794.4207819187403"/>
		<Force x="-232.12721582450433" y="988.0622954033554" z="-1160.5232843937572"/>
		<Force x="-687.6369715501141" y="840.9563042228133" z="909.7019238285518"/>
		<Force x="-271.39258496717156" y="123.67709951900846" z="-260.98863747615445"/>
		<Force x="859.9370101597376" y="-1539.2702393864245" z="859.8799603930136"/>
		<Force x="-604.457358486945" y="645.6922369201179" z="206.96861116462972"/>
		<Force x="-342.2482153211474" y="-1405.583474581698" z="-282.7677548231641"/>
		<Force x="411.3232551976577" y="1812.6768172944035" z="81.56343369532219"/>
		<Force x="287.68701619374826" y="724.0158422676003" z="292.5452010207435"/>
		<Force x="497.53408418341104" y=".9347517734981432" z="160.74151082069412"/>
		<Force x="-185.19077169245207" y="73.95250368316978" z="191.8286286297897"/>
		<Force x="-628.1970038829851" y="-40.809549482976195" z="136.3796700463921"/>
		<Force x="-239.39498618509566" y="-339.4505533141022" z="-415.2448028721977"/>
		<Force x="-137.49707646873347" y="-253.75133018531162" z="-436.34172858827634"/>
		<Force x="61.06670855222255" y="12.852121173938713" z="139.75636637293056"/>
		<Force x="42.33369998426755" y="225.3172672994224" z="162.88982007927018"/>
		<Force x="-34.765514795695886" y="-32.4537326327916" z="295.7949973354688"/>
		<Force x="-5.631420444099215" y="-375.0851893410746" z="-474.2790037134849"/>
		<Force x="25.371791090168387" y="-157.649112529556" z="33.333896350551015"/>
		<Force x="-445.955308946315" y="331.513822459098" z="-364.77431968462673"/>
		<Force x="18.406509700765486" y="108.48849596730012" z="40.85448633355394"/>
	</Forces>
	<IntegratorParameters/>
</State>
