<?xml version="1.0" ?>
<State openmmVersion="7.5.1" time="200.00000000022686" type="State" version="1">
	<PeriodicBoxVectors>
		<A x="3.4000000000000004" y="0" z="0"/>
		<B x="0" y="3.4000000000000004" z="0"/>
		<C x="0" y="0" z="3.4000000000000004"/>
	</PeriodicBoxVectors>
	<Parameters lambda_electrostatics="1" lambda_sterics="1"/>
	<Positions>
		<Position x=".43701922209414196" y=".5678439329763054" z=".4741280141470123"/>
		<Position x=".4296301874689062" y=".5027830900972408" z=".3874882490778483"/>
		<Position x=".5349089151195208" y=".4115174254950511" z=".36604087161495513"/>
		<Position x=".531678120780902" y=".3355155174882978" z=".25081237334517126"/>
		<Position x=".4186842845039632" y=".3458539219246378" z=".16737754372039929"/>
		<Position x=".3186081564757895" y=".4361893704291184" z=".19098947168292574"/>
		<Position x=".320415305662496" y=".5201564899861284" z=".30010729373065803"/>
		<Position x=".2448707897482781" y=".5944178760504696" z=".32402867862225043"/>
		<Position x=".2270502330380174" y=".4197476783657488" z=".08286033574248494"/>
		<Position x=".2694768790570673" y=".30471605394219886" z=".016336542521240737"/>
		<Position x=".3937701470436579" y=".2741336770695068" z=".05682617182774644"/>
		<Position x=".47044732529524025" y=".2330133875208895" z=".005535508702095668"/>
		<Position x=".1933077166538232" y=".25053378349342553" z="-.1040129208359483"/>
		<Position x=".1402083505032386" y=".322180820285631" z="-.16788040450854197"/>
		<Position x=".11873942376569539" y=".17532195393701538" z="-.07547091711161594"/>
		<Position x=".2656714419372301" y=".1989270981463907" z="-.16829462170162737"/>
		<Position x=".13313364649553253" y=".4709057256648876" z=".0653507420909685"/>
		<Position x=".6075332915348634" y=".26176400559162016" z=".22630385313165316"/>
		<Position x=".6145903693375668" y=".3922910509354659" z=".43728111568383426"/>
	</Positions>
	<Velocities>
		<Velocity x="-2.0692182432743564" y="-.3626551114464527" z=".031205170712644836"/>
		<Velocity x=".5086587822558386" y="-.25505341990844643" z="-.3479447738906627"/>
		<Velocity x=".5327184411684227" y="-.32636428887672375" z=".613571564898413"/>
		<Velocity x="-.2482060677451714" y=".43672367172611914" z="-.035061303986616554"/>
		<Velocity x="-.5692237322816596" y=".621425446347551" z="-.06192018954075118"/>
		<Velocity x=".10452833836177566" y="-.021880033102134044" z=".1477424438209446"/>
		<Velocity x="-.6220156346971317" y="-.07677907515268867" z="-.4810192729878815"/>
		<Velocity x=".21982207191707792" y=".5593374770112014" z=".27309012413601064"/>
		<Velocity x=".8222235768260144" y="-.5684035927903675" z="1.0015534395282564"/>
		<Velocity x=".5157926319384609" y="-.6652600689033283" z="-.10065052255277956"/>
		<Velocity x=".17806894119082317" y=".7150087434268371" z="-.8458833822421672"/>
		<Velocity x="1.4469450450315668" y="-.7326730945781124" z="1.9833375032983076"/>
		<Velocity x="-1.1041606302736318" y=".15169937472600536" z="-.14848155390462248"/>
		<Velocity x="-1.1608565425686446" y=".4413334392588675" z=".22006834183489754"/>
		<Velocity x="-1.0608677054270155" y=".3412607921145089" z=".4792922044182524"/>
		<Velocity x=".8302441252059922" y=".7224387040437458" z="1.467041572948344"/>
		<Velocity x="1.1939598327637553" y="-.6700013620556944" z="-1.7209789756701608"/>
		<Velocity x="-3.1302164371905805" y="-3.0263860310150994" z=".6204410744027056"/>
		<Velocity x="-.28877067555538316" y="-.4125592798370492" z="1.5305152212724826"/>
	</Velocities>
	<Forces>
		<Force x="-160.46226759352476" y="-113.5986015637685" z="107.58605387057871"/>
		<Force x="351.86260228589856" y="926.3036329285673" z="943.5357856756593"/>
		<Force x="-225.49463687114" y="-146.59416227449398" z="27.320914186914862"/>
		<Force x="-541.5173153836325" y="-1023.4398734823678" z="-1225.0460507974185"/>
		<Force x="679.8329184954965" y="794.7634095889997" z="1416.123475925963"/>
		<Force x="123.04994085443514" y="-426.53532269889376" z="-899.0145710985487"/>
		<Force x="559.6001352805167" y="200.32933280248758" z="914.1257564247032"/>
		<Force x="-216.50156893760146" y="-107.93526039654677" z="-382.08492887553075"/>
		<Force x="-623.7780888158175" y="-644.0991830418415" z="130.56273270124677"/>
		<Force x="-2666.977560726706" y="1269.047482865286" z="-1577.1454307086933"/>
		<Force x="2336.0008101423323" y="-675.759726917198" z="28.42366374687212"/>
		<Force x="-570.8474404025068" y="-472.3503019904218" z="-307.9167738073558"/>
		<Force x="587.3070390614376" y="-658.4766813855858" z="-.9815416128499046"/>
		<Force x="200.17862494842853" y="414.9442565317258" z="295.4232635097978"/>
		<Force x="62.53628882177087" y="16.910672118253846" z="203.0271165129645"/>
		<Force x="-112.89202277010325" y="-12.108805046944001" z="-115.7518755603732"/>
		<Force x="40.3524510660941" y="77.52867021354305" z="36.30133517612484"/>
		<Force x="151.99610558262458" y="77.46341273800134" z="271.76157053218463"/>
		<Force x="25.73199030182891" y="503.61527142654586" z="133.7727155263264"/>
	</Forces>
	<IntegratorParameters/>
</State>
